MANIFEST.in
README.rst
base.cfg
bootstrap.py
buildout.cfg
plonetheme.bootstrap-configure.zcml
setup.py
docs/HISTORY.txt
docs/INSTALL.txt
docs/LICENSE.GPL
docs/LICENSE.txt
plonetheme/__init__.py
plonetheme.bootstrap.egg-info/PKG-INFO
plonetheme.bootstrap.egg-info/SOURCES.txt
plonetheme.bootstrap.egg-info/dependency_links.txt
plonetheme.bootstrap.egg-info/entry_points.txt
plonetheme.bootstrap.egg-info/namespace_packages.txt
plonetheme.bootstrap.egg-info/not-zip-safe
plonetheme.bootstrap.egg-info/requires.txt
plonetheme.bootstrap.egg-info/top_level.txt
plonetheme/bootstrap/__init__.py
plonetheme/bootstrap/configure.zcml
plonetheme/bootstrap/profiles.zcml
plonetheme/bootstrap/setuphandlers.py
plonetheme/bootstrap/testing.py
plonetheme/bootstrap/upgrades.py
plonetheme/bootstrap/Extensions/Install.py
plonetheme/bootstrap/Extensions/__init__.py
plonetheme/bootstrap/browser/__init__.py
plonetheme/bootstrap/browser/bootstrap-integration.js
plonetheme/bootstrap/browser/configure.zcml
plonetheme/bootstrap/browser/dropdownmenu.pt
plonetheme/bootstrap/browser/dropdownmenu.py
plonetheme/bootstrap/browser/interfaces.py
plonetheme/bootstrap/browser/navigation.py
plonetheme/bootstrap/browser/utils.py
plonetheme/bootstrap/browser/templates/.DS_Store
plonetheme/bootstrap/browser/templates/Products.TinyMCE.skins.tinymce.plugins.plonebrowser.css.plonebrowser.css
plonetheme/bootstrap/browser/templates/Products.TinyMCE.skins.tinymce.plugins.plonebrowser.js.plonebrowser.js
plonetheme/bootstrap/browser/templates/Products.TinyMCE.skins.tinymce.plugins.plonebrowser.plonebrowser.htm.pt
plonetheme/bootstrap/browser/templates/plone.app.contentmenu.contentmenu.pt
plonetheme/bootstrap/browser/templates/plone.app.controlpanel.control-panel.pt
plonetheme/bootstrap/browser/templates/plone.app.controlpanel.overview.pt
plonetheme/bootstrap/browser/templates/plone.app.iterate.browser.info_baseline.pt
plonetheme/bootstrap/browser/templates/plone.app.iterate.browser.info_checkout.pt
plonetheme/bootstrap/browser/templates/plone.app.layout.viewlets.contentactions.pt
plonetheme/bootstrap/browser/templates/plone.app.layout.viewlets.contentviews.pt
plonetheme/bootstrap/browser/templates/plone.app.layout.viewlets.logo.pt
plonetheme/bootstrap/browser/templates/plone.app.layout.viewlets.manage_portlets_fallback.pt
