Metadata-Version: 2.1
Name: plonetheme.bootstrap
Version: 2.0.1
Summary: bootstrap css integration
Home-page: https://github.com/collective/plonetheme.bootstrap
Author: Nathan van Gheem, Mikel Larreategi
Author-email: mlarreategi@codesyntax.com
License: GPL
Keywords: plone theme twitterbootstrap
Platform: UNKNOWN
Classifier: Framework :: Plone
Classifier: Programming Language :: Python
Provides-Extra: test
